README.md
setup.py
numpyp2/.env
numpyp2/__init__.py
numpyp2/code.py
numpyp2/code_t.py
numpyp2/see.py
numpyp2/telegram_handler.py
numpyp2.egg-info/PKG-INFO
numpyp2.egg-info/SOURCES.txt
numpyp2.egg-info/dependency_links.txt
numpyp2.egg-info/requires.txt
numpyp2.egg-info/top_level.txt
numpyp2/theory/__init__.py